mini_photoshop/__init__.py
mini_photoshop/gui.py
mini_photoshop/utils.py
mini_photoshop/model/__init__.py
mini_photoshop/model/lama.py
mini_photoshop/model/u2net.py
mini_photoshop-0.1.1.dist-info/METADATA
mini_photoshop-0.1.1.dist-info/WHEEL
mini_photoshop-0.1.1.dist-info/entry_points.txt
mini_photoshop-0.1.1.dist-info/top_level.txt
mini_photoshop-0.1.1.dist-info/RECORD
