Metadata-Version: 2.1
Name: mini-photoshop
Version: 0.1.1
Summary: Mini photoshop tool
Home-page: 
Author: Tung Tien Bui
Author-email: tungbui198.hust@gmail.com
License: UNKNOWN
Platform: UNKNOWN
Classifier: Programming Language :: Python :: 3
Classifier: License :: OSI Approved :: MIT License
Classifier: Operating System :: OS Independent
Requires-Python: >=3.8
Requires-Dist: torch (>=1.11.0)
Requires-Dist: scikit-image (==0.19.3)
Requires-Dist: tqdm
Requires-Dist: gdown
Requires-Dist: opencv-python
Requires-Dist: streamlit
Requires-Dist: streamlit-drawable-canvas
